<?xml version='1.0' encoding='utf-8'?>
<odoo>

    <!-- Mini Cart Template-->
<template id="mini_cart_bits" name="Shop Mini Cart">
    <div class="mini-cart-style-bits">
        <div class="empty-div"></div>
        <t t-if="not website_sale_order or not website_sale_order.website_order_line">
            <t t-call="theme_crest.empty_mini_cart_bits"/>
        </t>
        <div class="cart_body" t-if="website_sale_order and website_sale_order.website_order_line">
            <div class="row cart-body-bits">
                <div class="col-lg-6 col-12">
                    <t t-call="theme_crest.mini_cart_lines_bits"/>
                </div>
                <div class="col-lg-6 col-12">
                    <div class="cart-summary-bits">
                        <t t-call="website_sale.total"/>
                    </div>
                </div>
            </div> 
        </div>
        <div class="cart-btn-bar-bits">
            <a href="/shop/cart" class="btn btn-view-bits btn-primary">View Cart</a>
            <a href="/shop/checkout" class="btn-checkout-bits btn btn-secondary">Checkout</a>
        </div>
    </div>
</template>

<!-- Mini Cart Lines -->
<template id="mini_cart_lines_bits" name="Shop Mini Cart lines">
    <div class="mini-main-cart-bits">
        <ul class="mini-cart-products-bits">
            <t t-foreach="website_sale_order.website_order_line" t-as="line" t-attf-class="#{'optional_product info'}">
                <li class="mc-media-bits">
                    <div class="mc-img-bits">
                        <t t-if="line.product_id.product_tmpl_id">
                            <span t-field="line.product_id.image_128"
                                  t-options="{'widget': 'image', 'qweb_img_responsive': False, 'class': 'rounded '}" />
                        </t>
                    </div>
                    <div class="mc-info-bits">
                        <h6>
                            <a t-attf-href="/shop/product/{{line.product_id.product_tmpl_id.id}}">
                                <t t-esc="line.product_id.with_context(display_default_code=False).display_name"/>
                            </a>
                            <t t-call="website_sale.cart_line_description_following_lines">
                                <t t-set="div_class" t-value="'cart-description'"/>
                            </t>
                        </h6>
                        <div class="m_c_prod_price">
                            <t t-if="line.discount">
                                <del class="text-danger mr8"
                                     style="white-space: nowrap;"
                                     t-out="line.price_unit * line.product_uom_qty"
                                     t-options="{'widget': 'monetary', 'display_currency': website.currency_id}"/>
                            </t>
                            <t t-if="website.show_line_subtotals_tax_selection == 'tax_excluded'" t-set='product_price' t-value='line.price_subtotal'/>
                            <t t-else="" t-set='product_price' t-value='line.price_total'/>
                            <span t-out="product_price"
                                  style="white-space: nowrap; display:inline-block; padding: 5px 0px;"
                                  t-options="{'widget': 'monetary', 'display_currency': website_sale_order.currency_id}"/>
                            <small t-if="not line._is_not_sellable_line() and line.product_id.base_unit_price"
                                   class="cart_product_base_unit_price d-block text-muted"
                                   groups="website_sale.group_show_uom_price">
                                <t t-call='website_sale.base_unit_price'>
                                    <t t-set='product' t-value='line.product_id'/>
                                    <t t-set='combination_info' t-value="{'base_unit_price':product._get_base_unit_price(product_price)}"/>
                                </t>
                            </small>
                        </div>

                        <div class="m_c_qty">
                            <div class="css_quantity input-group">
                                <div class="input-group-prepend">
                                    <a href="#"
                                       class="btn btn-link css_quantity_minus js_add_cart_json rounded-0 d-md-inline-block"
                                       aria-label="Remove one" title="Remove one"
                                       t-att-data-line-id="line.id"
                                       t-att-data-product-id="line.product_id.id"
                                       data-action="decrease">
                                        <i class="fa fa-minus"/>
                                    </a>
                                </div>
                                <input type="text"
                                       t-attf-class="js_quantity form-control quantity p-1 text-center sale_line_#{line.product_id.id}"
                                       t-att-data-line-id="line.id"
                                       t-att-data-product-id="line.product_id.id"
                                       t-att-value="int(line.product_uom_qty) == line.product_uom_qty and int(line.product_uom_qty) or line.product_uom_qty"/>
                                <div class="input-group-append">
                                    <a href="#"
                                       class="btn btn-link css_quantity_plus rounded-0 float_left js_add_cart_json d-md-inline-block"
                                       aria-label="Add one" title="Add one"
                                       t-att-data-line-id="line.id"
                                       t-att-data-product-id="line.product_id.id"
                                       data-action="increase">
                                        <i class="fa fa-plus"/>
                                    </a>
                                </div>
                            </div>
                            <a href="#"
                               aria-label="Remove from cart" title="Remove from cart"
                               class="js_delete_product no-decoration"
                               t-att-data-line-id="line.id"
                               t-att-data-product-id="line.product_id.id"
                               data-action="remove">
                                <i class="fa fa-trash-o"></i>
                            </a>
                        </div>
                    </div>
                </li>
            </t>
        </ul>

        <div t-if="suggested_products and len(suggested_products)" class="min-suggested-bits">
            <div id="suggestedProductControls">
                <h5 class="mini-title-bits" t-if="suggested_products">Suggested Accessories</h5>
                <div>
                    <t t-foreach="suggested_products" t-as="suggested_prod">
                        <div class="min-sa-pro-bits">
                            <div class="sa-img-bits">
                                <a t-att-href="suggested_prod.website_url">
                                    <span t-field="suggested_prod.image_128"
                                          t-options="{'widget': 'image', 'qweb_img_responsive': False, 'class': ''}" />
                                </a>
                            </div>
                            <div class="sa-info-bits">
                                <h6>
                                    <a t-att-href="suggested_prod.website_url"><t t-esc="suggested_prod.name"/></a>
                                </h6>
                                <div class="m_c_prod_price">
                                    <h6 class="oe_price_h4 css_editable_mode_hidden">
                                        <t t-set="combination_info" t-value="suggested_prod._get_combination_info_variant()"/>
                                        <del class="text-danger mr8"
                                             t-attf-class="{{'' if combination_info['has_discounted_price'] else 'd-none'}}"
                                             t-esc="combination_info['list_price']"
                                             t-options="{'widget': 'monetary', 'display_currency': website.currency_id}"
                                             style="white-space: nowrap;"/>
                                        <span t-esc="combination_info['price']"
                                              t-options="{'widget': 'monetary','display_currency': website.currency_id}"
                                              style="white-space: nowrap; display:inline-block; padding: 5px 0px;"/>
                                    </h6>
                                </div>
                                <div class="sa-btn-bits">
                                    <input class="js_quantity"
                                           name="product_id"
                                           t-att-data-product-id="suggested_prod.id"
                                           t-att-data-product-list="website_sale_order.website_order_line.product_id.mapped('id')"
                                           type="hidden"/>
                                    <a t-if="suggested_prod.sudo()._website_show_quick_add()"
                                       role="button"
                                       class="js_add_suggested_products btn text-nowrap"
                                       t-att-data-product-id="suggested_prod.id">
                                        <span><i class="fa fa-shopping-basket"></i></span>
                                    </a>
                                </div>
                            </div>
                        </div>
                    </t>
                </div>
            </div>
        </div>
    </div>
</template>
    <!-- Empty Mini Cart -->
    <template id="empty_mini_cart_bits" name="Shop Empty Cart lines">
        <div class="mini-cart-empty-bits">
            <div>
                <svg width="527" height="405" viewBox="0 0 527 405" fill="none" xmlns="http://www.w3.org/2000/svg" style="width: 200px;height: auto;">
                    <path d="M41.634 370.844C54.0624 393.893 80.44 403.787 80.44 403.787C80.44 403.787 86.6671 376.312 74.2387 353.263C61.8103 330.214 35.4327 320.319 35.4327 320.319C35.4327 320.319 29.2056 347.795 41.634 370.844Z" fill="#2F2E41" />
                    <path d="M419.647 297.511C400.271 315.126 397.022 343.11 397.022 343.11C397.022 343.11 425.188 342.535 444.565 324.921C463.941 307.306 467.19 279.321 467.19 279.321C467.19 279.321 439.024 279.896 419.647 297.511Z" fill="#2F2E41" />
                    <path d="M50.1765 363.261C72.6149 376.761 81.2567 403.575 81.2567 403.575C81.2567 403.575 53.5186 408.502 31.0802 395.002C8.64174 381.502 0 354.688 0 354.688C0 354.688 27.7381 349.761 50.1765 363.261Z" fill="var(--primary)" />
                    <path d="M429.065 303.975C421.368 329.005 397.425 343.852 397.425 343.852C397.425 343.852 385.962 318.117 393.659 293.087C401.356 268.058 425.298 253.211 425.298 253.211C425.298 253.211 436.762 278.946 429.065 303.975Z" fill="var(--primary)" />
                    <path d="M362.06 360.29H125.274V358.587H360.356V275.967H145.18L134.727 254.19L136.263 253.453L146.252 274.263H362.06V360.29Z" fill="#2F2E41" />
                    <path d="M156.789 402.026C166.667 402.026 174.675 394.018 174.675 384.139C174.675 374.26 166.667 366.252 156.789 366.252C146.91 366.252 138.902 374.26 138.902 384.139C138.902 394.018 146.91 402.026 156.789 402.026Z" fill="#3F3D56" />
                    <path d="M333.101 402.026C342.979 402.026 350.987 394.018 350.987 384.139C350.987 374.26 342.979 366.252 333.101 366.252C323.222 366.252 315.214 374.26 315.214 384.139C315.214 394.018 323.222 402.026 333.101 402.026Z" fill="#3F3D56" />
                    <path d="M387.385 247.859H121.237L63.6484 59.6227H446.693L446.344 60.7302L387.385 247.859ZM122.497 246.156H386.136L444.37 61.3262H65.9508L122.497 246.156Z" fill="#2F2E41" />
                    <path d="M366.61 238.064H132.842L82.26 71.121H418.701L418.395 72.104L366.61 238.064Z" fill="#F2F2F2" />
                    <path d="M451.465 42.806L449.818 42.369L461.059 0H526.448V1.70398H462.37L451.465 42.806Z" fill="#2F2E41" />
                    <path d="M427.552 116.69H82.2584V118.393H427.552V116.69Z" fill="#2F2E41" />
                    <path d="M407.777 179.45H101.459V181.153H407.777V179.45Z" fill="#2F2E41" />
                    <path d="M256.017 60.4744H254.314V247.007H256.017V60.4744Z" fill="#2F2E41" />
                    <path d="M332.286 60.421L320.057 246.949L321.758 247.061L333.986 60.5324L332.286 60.421Z" fill="#2F2E41" />
                    <path d="M178.081 60.419L176.38 60.5298L188.538 247.063L190.238 246.952L178.081 60.419Z" fill="#2F2E41" />
                </svg>
            </div>
            <p>Your Shopping Cart is empty</p>
            <div class="button">
                <a href="/shop" class="btn btn-bits-shop btn-primary">Shop Now</a>
            </div>
        </div>
    </template>
</odoo>